{
  "parent": "item/handheld",
  "textures": {
    "layer0": "item/bow"
  },
  "overrides": [
    {
      "predicate": {
        "theancientworld:bow_of_arrows_pulling": 1
      },
      "model": "item/bow_pulling_0"
    },
    {
      "predicate": {
        "theancientworld:bow_of_arrows_pulling": 1,
        "theancientworld:bow_of_arrows_pull": 0.4
      },
      "model": "item/bow_pulling_1"
    },
    {
      "predicate": {
        "theancientworld:bow_of_arrows_pulling": 1,
        "theancientworld:bow_of_arrows_pull": 0.65
      },
      "model": "item/bow_pulling_2"
    },
    {
      "predicate": {
        "theancientworld:bow_of_arrows_pulling": 1,
        "theancientworld:bow_of_arrows_pull": 0.9
      },
      "model": "theancientworld:item/vasilis_3"
    }
  ]
}